jupyterlab_change_ui_font_size_fix/__init__.py
jupyterlab_change_ui_font_size_fix/_version.py
jupyterlab_change_ui_font_size_fix-1.0.8.data/data/share/jupyter/labextensions/jupyterlab_change_ui_font_size_fix/package.json
jupyterlab_change_ui_font_size_fix-1.0.8.data/data/share/jupyter/labextensions/jupyterlab_change_ui_font_size_fix/static/509.59dae844e601e82ac445.js
jupyterlab_change_ui_font_size_fix-1.0.8.data/data/share/jupyter/labextensions/jupyterlab_change_ui_font_size_fix/static/728.8e50c248259814e4a1d6.js
jupyterlab_change_ui_font_size_fix-1.0.8.data/data/share/jupyter/labextensions/jupyterlab_change_ui_font_size_fix/static/remoteEntry.49308716ae112162efb1.js
jupyterlab_change_ui_font_size_fix-1.0.8.data/data/share/jupyter/labextensions/jupyterlab_change_ui_font_size_fix/static/style.js
jupyterlab_change_ui_font_size_fix-1.0.8.data/data/share/jupyter/labextensions/jupyterlab_change_ui_font_size_fix/static/third-party-licenses.json
jupyterlab_change_ui_font_size_fix-1.0.8.data/data/share/jupyter/labextensions/jupyterlab_change_ui_font_size_fix/install.json
jupyterlab_change_ui_font_size_fix-1.0.8.dist-info/METADATA
jupyterlab_change_ui_font_size_fix-1.0.8.dist-info/WHEEL
jupyterlab_change_ui_font_size_fix-1.0.8.dist-info/licenses/LICENSE
jupyterlab_change_ui_font_size_fix-1.0.8.dist-info/RECORD
